bakta/__init__.py
bakta/config.py
bakta/constants.py
bakta/db.py
bakta/ips.py
bakta/json_io.py
bakta/main.py
bakta/plot.py
bakta/proteins.py
bakta/psc.py
bakta/pscc.py
bakta/so.py
bakta/ups.py
bakta/utils.py
bakta/expert/__init__.py
bakta/expert/amrfinder.py
bakta/expert/protein_hmms.py
bakta/expert/protein_sequences.py
bakta/features/__init__.py
bakta/features/annotation.py
bakta/features/cds.py
bakta/features/crispr.py
bakta/features/gaps.py
bakta/features/nc_rna.py
bakta/features/nc_rna_region.py
bakta/features/orf.py
bakta/features/ori.py
bakta/features/r_rna.py
bakta/features/s_orf.py
bakta/features/t_rna.py
bakta/features/tm_rna.py
bakta/io/__init__.py
bakta/io/fasta.py
bakta/io/gff.py
bakta/io/insdc.py
bakta/io/json.py
bakta/io/tsv.py
bakta-1.11.4.dist-info/licenses/LICENSE
bakta-1.11.4.dist-info/METADATA
bakta-1.11.4.dist-info/WHEEL
bakta-1.11.4.dist-info/entry_points.txt
bakta-1.11.4.dist-info/top_level.txt
bakta-1.11.4.dist-info/RECORD
