Metadata-Version: 2.4
Name: bakta
Version: 1.11.4
Summary: Bakta: rapid & standardized annotation of bacterial genomes, MAGs & plasmids
Home-page: https://github.com/oschwengers/bakta
Author: Oliver Schwengers
Author-email: oliver.schwengers@computational.bio.uni-giessen.de
License: GPLv3
Project-URL: Documentation, https://bakta.readthedocs.io
Project-URL: Source, https://github.com/oschwengers/bakta
Project-URL: Bug Reports, https://github.com/oschwengers/bakta/issues
Project-URL: CI, https://github.com/oschwengers/bakta/actions
Keywords: bioinformatics,annotation,bacteria,plasmids
Classifier: Operating System :: POSIX :: Linux
Classifier: Programming Language :: Python :: 3 :: Only
Classifier: Programming Language :: Python :: 3.9
Classifier: Programming Language :: Python :: 3.10
Classifier: Programming Language :: Python :: 3.11
Classifier: Development Status :: 5 - Production/Stable
Classifier: License :: OSI Approved :: GNU General Public License v3 (GPLv3)
Classifier: Topic :: Scientific/Engineering :: Bio-Informatics
Classifier: Environment :: Console
Classifier: Intended Audience :: Science/Research
Classifier: Natural Language :: English
Requires-Python: >=3.9, <3.12
License-File: LICENSE
Requires-Dist: biopython>=1.78
Requires-Dist: xopen>=1.5.0
Requires-Dist: requests>=2.25.1
Requires-Dist: alive-progress>=3.0.1
Requires-Dist: PyYAML>=6.0
Requires-Dist: pyrodigal>=3.5.0
Requires-Dist: pyhmmer>=0.10.15
Requires-Dist: pycirclize>=1.7.0
Dynamic: author
Dynamic: author-email
Dynamic: classifier
Dynamic: description
Dynamic: description-content-type
Dynamic: home-page
Dynamic: keywords
Dynamic: license
Dynamic: license-file
Dynamic: project-url
Dynamic: requires-dist
Dynamic: requires-python
Dynamic: summary
